gen5/__init__.py
gen5/chunks/__init__.py
gen5/chunks/env.py
gen5/chunks/image.py
gen5/chunks/latent.py
gen5/chunks/metadata.py
gen5/core/__init__.py
gen5/core/constants.py
gen5/core/exceptions.py
gen5/core/header.py
gen5/handlers/__init__.py
gen5/handlers/file_handler.py
gen5-0.1.0.dist-info/licenses/LICENSE
gen5-0.1.0.dist-info/METADATA
gen5-0.1.0.dist-info/WHEEL
gen5-0.1.0.dist-info/top_level.txt
gen5-0.1.0.dist-info/RECORD
