Metadata-Version: 2.4
Name: gen5
Version: 0.1.0
Summary: GEN5: A Binary Container Format For Improving Reproducibility In Workflows Concerning AI-Generated Images
Author-email: Anuroop V J <anuroopvjneelambari@gmail.com>
License-Expression: MIT
Project-URL: Homepage, https://pypi.org/project/gen5/
Project-URL: Repository, https://github.com/AnuroopVJ/gen5
Project-URL: Documentation, https://github.com/AnuroopVJ/gen5/tree/master/all_docs/docs
Keywords: image-format,encoder,decoder,gen5
Classifier: Development Status :: 3 - Alpha
Classifier: Intended Audience :: Developers
Classifier: Intended Audience :: Science/Research
Classifier: Programming Language :: Python :: 3
Classifier: Programming Language :: Python :: 3.9
Classifier: Programming Language :: Python :: 3.10
Classifier: Programming Language :: Python :: 3.11
Classifier: Programming Language :: Python :: 3.12
Classifier: Programming Language :: Python :: 3 :: Only
Classifier: Operating System :: OS Independent
Classifier: Topic :: Multimedia :: Graphics
Classifier: Topic :: Software Development :: Libraries :: Python Modules
Requires-Python: >=3.9
License-File: LICENSE
Requires-Dist: click
Requires-Dist: jsonschema
Requires-Dist: numpy
Requires-Dist: pillow
Requires-Dist: pynvml
Requires-Dist: torch
Requires-Dist: typing-extensions
Requires-Dist: zstandard
Provides-Extra: dev
Requires-Dist: pytest>=7.0; extra == "dev"
Requires-Dist: pytest-cov; extra == "dev"
Requires-Dist: ruff>=0.1.0; extra == "dev"
Requires-Dist: mypy>=1.0; extra == "dev"
Requires-Dist: types-Pillow; extra == "dev"
Dynamic: license-file
